sc_kpm/__init__.py
sc_kpm/identifiers.py
sc_kpm/logging.py
sc_kpm/sc_agent.py
sc_kpm/sc_keynodes.py
sc_kpm/sc_module.py
sc_kpm/sc_result.py
sc_kpm/sc_server.py
sc_kpm/sc_sets/__init__.py
sc_kpm/sc_sets/sc_numbered_set.py
sc_kpm/sc_sets/sc_oriented_set.py
sc_kpm/sc_sets/sc_set.py
sc_kpm/sc_sets/sc_structure.py
sc_kpm/utils/__init__.py
sc_kpm/utils/action_utils.py
sc_kpm/utils/common_utils.py
sc_kpm/utils/iteration_utils.py
py_sc_kpm-0.3.0.dist-info/LICENSE
py_sc_kpm-0.3.0.dist-info/METADATA
py_sc_kpm-0.3.0.dist-info/WHEEL
py_sc_kpm-0.3.0.dist-info/top_level.txt
py_sc_kpm-0.3.0.dist-info/RECORD
