Metadata-Version: 2.1
Name: py-sc-kpm
Version: 0.3.0
Summary: The Python implementation of the knowledge processing module for knowledge manipulations
Home-page: https://github.com/ostis-ai/py-sc-kpm
Author: ostis-ai
License: MIT
Project-URL: Bug Reports, https://github.com/ostis-ai/py-sc-kpm/issues
Project-URL: Source, https://github.com/ostis-ai/py-sc-kpm
Keywords: sc-kpm,kpm,knowledge processing
Classifier: Topic :: Software Development :: Libraries :: Python Modules
Classifier: Intended Audience :: Developers
Classifier: License :: OSI Approved :: MIT License
Classifier: Programming Language :: Python :: 3
Classifier: Programming Language :: Python :: 3.8
Classifier: Programming Language :: Python :: 3.9
Classifier: Programming Language :: Python :: 3.10
Requires-Python: >=3.8, <4
License-File: LICENSE
Requires-Dist: py-sc-client >=0.3.0
